modbus_client/__init__.py
modbus_client/modbus_client.py
modbus_client-0.0.5.dist-info/LICENSE
modbus_client-0.0.5.dist-info/WHEEL
modbus_client-0.0.5.dist-info/METADATA
modbus_client-0.0.5.dist-info/RECORD
